fastapi_logger/__init__.py
fastapi_logger/context.py
fastapi_logger/default_logger.py
nero_fastapi_logger_lib-0.1.6.dist-info/METADATA
nero_fastapi_logger_lib-0.1.6.dist-info/WHEEL
nero_fastapi_logger_lib-0.1.6.dist-info/top_level.txt
nero_fastapi_logger_lib-0.1.6.dist-info/RECORD
